README.txt
setup.py
tests/__init__.py
tests/comms/__init__.py
tests/comms/test_tcp_port.py
tests/data/__init__.py
tests/data/buffer/__init__.py
tests/data/buffer/test_ring_buffer.py
tests/io/__init__.py
tests/io/streamer/__init__.py
tests/io/streamer/test_em_streamer.py
tests/parser/__init__.py
tests/parser/alt/__init__.py
tests/parser/alt/test_hcsr04.py
tests/parser/alt/test_lidar_lite_v3.py
tests/parser/em/__init__.py
tests/parser/em/em3d/__init__.py
tests/parser/em/em3d/conf/__init__.py
tests/parser/em/em3d/conf/test_confv3.py
tests/parser/em/em3d/conf/test_confv5.py
tests/parser/em/em3d/em/__init__.py
tests/parser/em/em3d/em/test_emv1.py
tests/parser/em/em3d/em/test_emv2.py
tests/parser/imu/__init__.py
tests/parser/imu/microstrain/__init__.py
tests/parser/imu/microstrain/test_lord3dm_cv5.py
tests/parser/msgs/__init__.py
tests/parser/msgs/test_udp_wrapper.py
tests/parser/nmea/__init__.py
tests/parser/nmea/test_gpgga.py
tests/parser/nmea/test_gprmc.py
tests/parser/tfmag/__init__.py
tests/parser/tfmag/mfam/__init__.py
tests/parser/tfmag/mfam/test_m3xg.py
tests/parser/tfmag/qmag/__init__.py
tests/parser/tfmag/qmag/test_qmag.py
tests/parser/vmag/__init__.py
tests/parser/vmag/test_pni.py
wrtdk/__init__.py
wrtdk.egg-info/PKG-INFO
wrtdk.egg-info/SOURCES.txt
wrtdk.egg-info/dependency_links.txt
wrtdk.egg-info/not-zip-safe
wrtdk.egg-info/requires.txt
wrtdk.egg-info/top_level.txt
wrtdk/comms/__init__.py
wrtdk/comms/comms.py
wrtdk/data/__init__.py
wrtdk/data/wrt_data.py
wrtdk/data/buffer/__init__.py
wrtdk/data/buffer/buffer.py
wrtdk/data/state/__init__.py
wrtdk/data/state/state.py
wrtdk/dsp/__init__.py
wrtdk/dsp/filter/__init__.py
wrtdk/dsp/filter/dsp_filters.py
wrtdk/hardware/__init__.py
wrtdk/hardware/lora/__init__.py
wrtdk/hardware/lora/ebyte_e32.py
wrtdk/instrument/__init__.py
wrtdk/instrument/instrument.py
wrtdk/instrument/fieldfox/N9918A.py
wrtdk/instrument/fieldfox/__init__.py
wrtdk/io/__init__.py
wrtdk/io/writer.py
wrtdk/io/read/__init__.py
wrtdk/io/read/apex_reader.py
wrtdk/io/read/file_reader.py
wrtdk/io/read/tbsim_reader.py
wrtdk/io/sim/__init__.py
wrtdk/io/sim/apex_simulator.py
wrtdk/io/sim/sensor_simulator.py
