Metadata-Version: 1.0
Name: wrtdk
Version: 1.1.3.1
Summary: WRT Python 3 Libraries
Home-page: http://www.whiterivertech.com/
Author: Randall Reynolds
Author-email: reynolds@whiterivertech.com
License: MIT
Platform: UNKNOWN
